{
    "version": "0.22.1",
    "architecture": {
        "64bit": {
            "url": "https://github.com/marmos91/dittofs/releases/download/v0.22.1/dfsctl_0.22.1_Windows_x86_64.zip",
            "bin": [
                "dfsctl.exe"
            ],
            "hash": "c4a940ea7fa6823b4120727c6ef5143c4d70d1b3139d1f3aed34d50df7e86a6e"
        },
        "arm64": {
            "url": "https://github.com/marmos91/dittofs/releases/download/v0.22.1/dfsctl_0.22.1_Windows_arm64.zip",
            "bin": [
                "dfsctl.exe"
            ],
            "hash": "dc2dcf81d6354eb2c8b6d611967317a69bcc73408f0df465f3d0fd12e029bc97"
        }
    },
    "homepage": "https://github.com/marmos91/dittofs",
    "license": "MIT",
    "description": "DittoFS CLI client — remote management for DittoFS servers"
}
